findora/__init__.py
findora/prompts.py
findora-2025.7.131053.dist-info/licenses/LICENSE
tests/__init__.py
tests/conftest.py
tests/test_findora.py
findora-2025.7.131053.dist-info/METADATA
findora-2025.7.131053.dist-info/WHEEL
findora-2025.7.131053.dist-info/top_level.txt
findora-2025.7.131053.dist-info/RECORD
