Metadata-Version: 2.4
Name: findora
Version: 2025.7.131053
Summary: Search engine
Home-page: https://github.com/chigwell/findora
Author: Eugene Evstafev
Author-email: chigwel@gmail.com
License: MIT
Classifier: License :: OSI Approved :: MIT License
Classifier: Development Status :: 3 - Alpha
Classifier: Intended Audience :: Developers
Classifier: Programming Language :: Python :: 3
Classifier: Operating System :: OS Independent
Requires-Python: >=3.6
License-File: LICENSE
Requires-Dist: langchain_llm7==2025.4.101205
Requires-Dist: llmatch==2025.4.181303
Provides-Extra: test
Requires-Dist: pytest; extra == "test"
Requires-Dist: langchain_llm7==2025.4.101205; extra == "test"
Requires-Dist: llmatch==2025.4.181303; extra == "test"
Dynamic: author
Dynamic: author-email
Dynamic: classifier
Dynamic: description
Dynamic: description-content-type
Dynamic: home-page
Dynamic: license
Dynamic: license-file
Dynamic: provides-extra
Dynamic: requires-dist
Dynamic: requires-python
Dynamic: summary
